{
  "plan": [
    {
      "operator": "SemiJoin",
      "properties": {
        "viewName": "semiUp8777137127933163366",
        "columns": [
          "id",
          "title"
        ],
        "columnAliases": [
          "v12",
          "v13"
        ],
        "probeTable": "title AS t",
        "buildTable": "movie_info AS mi",
        "probeKeys": [
          "id"
        ],
        "buildKeys": [
          "movie_id"
        ],
        "innerConditions": [
          "(info = 'Bulgaria')"
        ],
        "outerConditions": [
          "(production_year > 2010)"
        ],
        "terminationPolicy": "ADAPTIVE"
      }
    },
    {
      "operator": "SemiJoin",
      "properties": {
        "viewName": "semiUp4856403789064204974",
        "columns": [
          "movie_id",
          "keyword_id"
        ],
        "columnAliases": [
          "v12",
          "v1"
        ],
        "probeTable": "movie_keyword AS mk",
        "buildTable": "keyword AS k",
        "probeKeys": [
          "keyword_id"
        ],
        "buildKeys": [
          "id"
        ],
        "innerConditions": [
          "(keyword LIKE '%sequel%')"
        ],
        "outerConditions": [],
        "terminationPolicy": "ADAPTIVE"
      }
    },
    {
      "operator": "SemiJoin",
      "properties": {
        "viewName": "semiUp8238462467863987795",
        "columns": [
          "",
          ""
        ],
        "columnAliases": [
          "v12",
          "v13"
        ],
        "probeTable": "semiUp8777137127933163366",
        "buildTable": "semiUp4856403789064204974",
        "probeKeys": [
          "v12"
        ],
        "buildKeys": [
          "v12"
        ],
        "innerConditions": [],
        "outerConditions": [],
        "terminationPolicy": "ADAPTIVE"
      }
    },
    {
      "operator": "SemiJoin",
      "properties": {
        "viewName": "semiDown8035915689623523328",
        "columns": [
          "movie_id"
        ],
        "columnAliases": [
          "v12"
        ],
        "probeTable": "movie_info AS mi",
        "buildTable": "semiUp8238462467863987795",
        "probeKeys": [
          "movie_id"
        ],
        "buildKeys": [
          "v12"
        ],
        "innerConditions": [],
        "outerConditions": [
          "(info = 'Bulgaria')"
        ],
        "terminationPolicy": "ADAPTIVE"
      }
    },
    {
      "operator": "SemiJoin",
      "properties": {
        "viewName": "semiDown3951226538004103911",
        "columns": [
          "",
          ""
        ],
        "columnAliases": [
          "v12",
          "v1"
        ],
        "probeTable": "semiUp4856403789064204974",
        "buildTable": "semiUp8238462467863987795",
        "probeKeys": [
          "v12"
        ],
        "buildKeys": [
          "v12"
        ],
        "innerConditions": [],
        "outerConditions": [],
        "terminationPolicy": "ADAPTIVE"
      }
    },
    {
      "operator": "SemiJoin",
      "properties": {
        "viewName": "semiDown6139388355286532566",
        "columns": [
          "id"
        ],
        "columnAliases": [
          "v1"
        ],
        "probeTable": "keyword AS k",
        "buildTable": "semiDown3951226538004103911",
        "probeKeys": [
          "id"
        ],
        "buildKeys": [
          "v1"
        ],
        "innerConditions": [],
        "outerConditions": [
          "(keyword LIKE '%sequel%')"
        ],
        "terminationPolicy": "ADAPTIVE"
      }
    },
    {
      "operator": "Select",
      "properties": {
        "viewName": "aggView7051732730920598541",
        "columns": [
          ""
        ],
        "columnAliases": [
          "v1"
        ],
        "inputView": "semiDown6139388355286532566",
        "conditions": [],
        "groupBy": []
      }
    },
    {
      "operator": "Join",
      "properties": {
        "viewName": "aggJoin9083617850730996388",
        "columns": [
          ""
        ],
        "columnAliases": [
          "v12"
        ],
        "probeTable": "semiDown3951226538004103911",
        "buildTable": "aggView7051732730920598541",
        "joinKeys": [
          "v1"
        ],
        "conditions": []
      }
    },
    {
      "operator": "GroupBy",
      "properties": {
        "viewName": "aggView544055090793769350",
        "columns": [
          ""
        ],
        "columnAliases": [
          "v12"
        ],
        "inputView": "aggJoin9083617850730996388",
        "conditions": [],
        "groupBy": [
          "v12"
        ],
        "terminationPolicy": "ADAPTIVE"
      }
    },
    {
      "operator": "Join",
      "properties": {
        "viewName": "aggJoin8021293423964526997",
        "columns": [
          "",
          ""
        ],
        "columnAliases": [
          "v12",
          "v13"
        ],
        "probeTable": "semiUp8238462467863987795",
        "buildTable": "aggView544055090793769350",
        "joinKeys": [
          "v12"
        ],
        "conditions": []
      }
    },
    {
      "operator": "GroupBy",
      "properties": {
        "viewName": "aggView6432707514694861815",
        "columns": [
          ""
        ],
        "columnAliases": [
          "v12"
        ],
        "inputView": "semiDown8035915689623523328",
        "conditions": [],
        "groupBy": [
          "v12"
        ],
        "terminationPolicy": "NONE"
      }
    },
    {
      "operator": "Join",
      "properties": {
        "viewName": "aggJoin7718991108529841966",
        "columns": [
          ""
        ],
        "columnAliases": [
          "v13"
        ],
        "probeTable": "aggJoin8021293423964526997",
        "buildTable": "aggView6432707514694861815",
        "joinKeys": [
          "v12"
        ],
        "conditions": []
      }
    },
    {
      "operator": "Select",
      "properties": {
        "viewName": "finalResult",
        "columns": [
          "v24"
        ],
        "columnAliases": [
          "v24"
        ],
        "inputView": "aggJoin7718991108529841966",
        "conditions": []
      }
    }
  ]
}