{
  "plan": [
    {
      "operator": "SemiJoin",
      "properties": {
        "viewName": "semiUp3535439469357476718",
        "columns": [
          "movie_id",
          "person_role_id",
          "role_id"
        ],
        "columnAliases": [
          "v31",
          "v1",
          "v29"
        ],
        "probeTable": "cast_info AS ci",
        "buildTable": "title AS t",
        "probeKeys": [
          "movie_id"
        ],
        "buildKeys": [
          "id"
        ],
        "innerConditions": [
          "(production_year > 1990)"
        ],
        "outerConditions": [
          "(note LIKE '%(producer)%')"
        ],
        "terminationPolicy": "ADAPTIVE"
      }
    },
    {
      "operator": "SemiJoin",
      "properties": {
        "viewName": "semiUp6131275593222966158",
        "columns": [
          "",
          "",
          ""
        ],
        "columnAliases": [
          "v31",
          "v1",
          "v29"
        ],
        "probeTable": "semiUp3535439469357476718",
        "buildTable": "char_name AS chn",
        "probeKeys": [
          "v1"
        ],
        "buildKeys": [
          "id"
        ],
        "innerConditions": [],
        "outerConditions": [],
        "terminationPolicy": "ADAPTIVE"
      }
    },
    {
      "operator": "SemiJoin",
      "properties": {
        "viewName": "semiUp6160708545897296882",
        "columns": [
          "movie_id",
          "company_id",
          "company_type_id"
        ],
        "columnAliases": [
          "v31",
          "v15",
          "v22"
        ],
        "probeTable": "movie_companies AS mc",
        "buildTable": "company_type AS ct",
        "probeKeys": [
          "company_type_id"
        ],
        "buildKeys": [
          "id"
        ],
        "innerConditions": [],
        "outerConditions": [],
        "terminationPolicy": "ADAPTIVE"
      }
    },
    {
      "operator": "SemiJoin",
      "properties": {
        "viewName": "semiUp5453507970523809773",
        "columns": [
          "",
          "",
          ""
        ],
        "columnAliases": [
          "v31",
          "v15",
          "v22"
        ],
        "probeTable": "semiUp6160708545897296882",
        "buildTable": "company_name AS cn",
        "probeKeys": [
          "v15"
        ],
        "buildKeys": [
          "id"
        ],
        "innerConditions": [
          "(country_code = '[us]')"
        ],
        "outerConditions": [],
        "terminationPolicy": "ADAPTIVE"
      }
    },
    {
      "operator": "SemiJoin",
      "properties": {
        "viewName": "semiUp2756940797135157068",
        "columns": [
          "",
          "",
          ""
        ],
        "columnAliases": [
          "v31",
          "v1",
          "v29"
        ],
        "probeTable": "semiUp6131275593222966158",
        "buildTable": "role_type AS rt",
        "probeKeys": [
          "v29"
        ],
        "buildKeys": [
          "id"
        ],
        "innerConditions": [],
        "outerConditions": [],
        "terminationPolicy": "ADAPTIVE"
      }
    },
    {
      "operator": "SemiJoin",
      "properties": {
        "viewName": "semiUp1437654104938301797",
        "columns": [
          "",
          "",
          ""
        ],
        "columnAliases": [
          "v31",
          "v15",
          "v22"
        ],
        "probeTable": "semiUp5453507970523809773",
        "buildTable": "semiUp2756940797135157068",
        "probeKeys": [
          "v31"
        ],
        "buildKeys": [
          "v31"
        ],
        "innerConditions": [],
        "outerConditions": [],
        "terminationPolicy": "ADAPTIVE"
      }
    },
    {
      "operator": "SemiJoin",
      "properties": {
        "viewName": "semiDown5093116494374660184",
        "columns": [
          "id"
        ],
        "columnAliases": [
          "v22"
        ],
        "probeTable": "company_type AS ct",
        "buildTable": "semiUp1437654104938301797",
        "probeKeys": [
          "id"
        ],
        "buildKeys": [
          "v22"
        ],
        "innerConditions": [],
        "outerConditions": [],
        "terminationPolicy": "ADAPTIVE"
      }
    },
    {
      "operator": "SemiJoin",
      "properties": {
        "viewName": "semiDown296771607380519320",
        "columns": [
          "id"
        ],
        "columnAliases": [
          "v15"
        ],
        "probeTable": "company_name AS cn",
        "buildTable": "semiUp1437654104938301797",
        "probeKeys": [
          "id"
        ],
        "buildKeys": [
          "v15"
        ],
        "innerConditions": [],
        "outerConditions": [
          "(country_code = '[us]')"
        ],
        "terminationPolicy": "ADAPTIVE"
      }
    },
    {
      "operator": "SemiJoin",
      "properties": {
        "viewName": "semiDown4709524062943119425",
        "columns": [
          "",
          "",
          ""
        ],
        "columnAliases": [
          "v31",
          "v1",
          "v29"
        ],
        "probeTable": "semiUp2756940797135157068",
        "buildTable": "semiUp1437654104938301797",
        "probeKeys": [
          "v31"
        ],
        "buildKeys": [
          "v31"
        ],
        "innerConditions": [],
        "outerConditions": [],
        "terminationPolicy": "ADAPTIVE"
      }
    },
    {
      "operator": "SemiJoin",
      "properties": {
        "viewName": "semiDown5849894003678126793",
        "columns": [
          "id"
        ],
        "columnAliases": [
          "v29"
        ],
        "probeTable": "role_type AS rt",
        "buildTable": "semiDown4709524062943119425",
        "probeKeys": [
          "id"
        ],
        "buildKeys": [
          "v29"
        ],
        "innerConditions": [],
        "outerConditions": [],
        "terminationPolicy": "ADAPTIVE"
      }
    },
    {
      "operator": "SemiJoin",
      "properties": {
        "viewName": "semiDown8569581457091970085",
        "columns": [
          "id",
          "title"
        ],
        "columnAliases": [
          "v31",
          "v32"
        ],
        "probeTable": "title AS t",
        "buildTable": "semiDown4709524062943119425",
        "probeKeys": [
          "id"
        ],
        "buildKeys": [
          "v31"
        ],
        "innerConditions": [],
        "outerConditions": [
          "(production_year > 1990)"
        ],
        "terminationPolicy": "ADAPTIVE"
      }
    },
    {
      "operator": "SemiJoin",
      "properties": {
        "viewName": "semiDown8376610313606308426",
        "columns": [
          "id",
          "name"
        ],
        "columnAliases": [
          "v1",
          "v2"
        ],
        "probeTable": "char_name AS chn",
        "buildTable": "semiDown4709524062943119425",
        "probeKeys": [
          "id"
        ],
        "buildKeys": [
          "v1"
        ],
        "innerConditions": [],
        "outerConditions": [],
        "terminationPolicy": "ADAPTIVE"
      }
    },
    {
      "operator": "Select",
      "properties": {
        "viewName": "aggView847060747257358853",
        "columns": [
          "",
          "v32"
        ],
        "columnAliases": [
          "v31",
          "v44"
        ],
        "inputView": "semiDown8569581457091970085",
        "conditions": [],
        "groupBy": []
      }
    },
    {
      "operator": "Join",
      "properties": {
        "viewName": "aggJoin8017024689343225384",
        "columns": [
          "",
          "",
          "",
          ""
        ],
        "columnAliases": [
          "v31",
          "v1",
          "v29",
          "v44"
        ],
        "probeTable": "semiDown4709524062943119425",
        "buildTable": "aggView847060747257358853",
        "joinKeys": [
          "v31"
        ],
        "conditions": []
      }
    },
    {
      "operator": "Select",
      "properties": {
        "viewName": "aggView6036198463201726407",
        "columns": [
          ""
        ],
        "columnAliases": [
          "v22"
        ],
        "inputView": "semiDown5093116494374660184",
        "conditions": [],
        "groupBy": []
      }
    },
    {
      "operator": "Join",
      "properties": {
        "viewName": "aggJoin6901557351886422932",
        "columns": [
          "",
          ""
        ],
        "columnAliases": [
          "v31",
          "v15"
        ],
        "probeTable": "semiUp1437654104938301797",
        "buildTable": "aggView6036198463201726407",
        "joinKeys": [
          "v22"
        ],
        "conditions": []
      }
    },
    {
      "operator": "Select",
      "properties": {
        "viewName": "aggView4516654689273850760",
        "columns": [
          ""
        ],
        "columnAliases": [
          "v29"
        ],
        "inputView": "semiDown5849894003678126793",
        "conditions": [],
        "groupBy": []
      }
    },
    {
      "operator": "Join",
      "properties": {
        "viewName": "aggJoin5995763744637186183",
        "columns": [
          "",
          "",
          ""
        ],
        "columnAliases": [
          "v31",
          "v1",
          "v44"
        ],
        "probeTable": "aggJoin8017024689343225384",
        "buildTable": "aggView4516654689273850760",
        "joinKeys": [
          "v29"
        ],
        "conditions": []
      }
    },
    {
      "operator": "Select",
      "properties": {
        "viewName": "aggView5648728165576306397",
        "columns": [
          ""
        ],
        "columnAliases": [
          "v15"
        ],
        "inputView": "semiDown296771607380519320",
        "conditions": [],
        "groupBy": []
      }
    },
    {
      "operator": "Join",
      "properties": {
        "viewName": "aggJoin5166951818487118441",
        "columns": [
          ""
        ],
        "columnAliases": [
          "v31"
        ],
        "probeTable": "aggJoin6901557351886422932",
        "buildTable": "aggView5648728165576306397",
        "joinKeys": [
          "v15"
        ],
        "conditions": []
      }
    },
    {
      "operator": "Select",
      "properties": {
        "viewName": "aggView3999143508710549637",
        "columns": [
          "",
          "v2"
        ],
        "columnAliases": [
          "v1",
          "v43"
        ],
        "inputView": "semiDown8376610313606308426",
        "conditions": [],
        "groupBy": []
      }
    },
    {
      "operator": "Join",
      "properties": {
        "viewName": "aggJoin6303410192638816582",
        "columns": [
          "",
          "",
          ""
        ],
        "columnAliases": [
          "v31",
          "v44",
          "v43"
        ],
        "probeTable": "aggJoin5995763744637186183",
        "buildTable": "aggView3999143508710549637",
        "joinKeys": [
          "v1"
        ],
        "conditions": []
      }
    },
    {
      "operator": "GroupBy",
      "properties": {
        "viewName": "aggView4813211122840119804",
        "columns": [
          "",
          "MIN(v44)",
          "MIN(v43)"
        ],
        "columnAliases": [
          "v31",
          "v44",
          "v43"
        ],
        "inputView": "aggJoin6303410192638816582",
        "conditions": [],
        "groupBy": [
          "v31",
          "v44",
          "v43"
        ],
        "terminationPolicy": "NONE"
      }
    },
    {
      "operator": "Join",
      "properties": {
        "viewName": "aggJoin6622717044937976262",
        "columns": [
          "",
          ""
        ],
        "columnAliases": [
          "v44",
          "v43"
        ],
        "probeTable": "aggJoin5166951818487118441",
        "buildTable": "aggView4813211122840119804",
        "joinKeys": [
          "v31"
        ],
        "conditions": []
      }
    },
    {
      "operator": "Select",
      "properties": {
        "viewName": "finalResult",
        "columns": [
          "MIN(v43)",
          "MIN(v44)"
        ],
        "columnAliases": [
          "v43",
          "v44"
        ],
        "inputView": "aggJoin6622717044937976262",
        "conditions": []
      }
    }
  ]
}