{
  "plan": [
    {
      "operator": "SemiJoin",
      "properties": {
        "viewName": "semiUp2367610003592225848",
        "columns": [
          "movie_id",
          "person_role_id",
          "role_id"
        ],
        "columnAliases": [
          "v31",
          "v1",
          "v29"
        ],
        "probeTable": "cast_info AS ci",
        "buildTable": "char_name AS chn",
        "probeKeys": [
          "person_role_id"
        ],
        "buildKeys": [
          "id"
        ],
        "innerConditions": [],
        "outerConditions": [
          "(note LIKE '%(producer)%')"
        ],
        "terminationPolicy": "ADAPTIVE"
      }
    },
    {
      "operator": "SemiJoin",
      "properties": {
        "viewName": "semiUp1592082984245895028",
        "columns": [
          "movie_id",
          "company_id",
          "company_type_id"
        ],
        "columnAliases": [
          "v31",
          "v15",
          "v22"
        ],
        "probeTable": "movie_companies AS mc",
        "buildTable": "company_type AS ct",
        "probeKeys": [
          "company_type_id"
        ],
        "buildKeys": [
          "id"
        ],
        "innerConditions": [],
        "outerConditions": [],
        "terminationPolicy": "ADAPTIVE"
      }
    },
    {
      "operator": "SemiJoin",
      "properties": {
        "viewName": "semiUp443217924677451287",
        "columns": [
          "",
          "",
          ""
        ],
        "columnAliases": [
          "v31",
          "v15",
          "v22"
        ],
        "probeTable": "semiUp1592082984245895028",
        "buildTable": "title AS t",
        "probeKeys": [
          "v31"
        ],
        "buildKeys": [
          "id"
        ],
        "innerConditions": [
          "(production_year > 2010)"
        ],
        "outerConditions": [],
        "terminationPolicy": "ADAPTIVE"
      }
    },
    {
      "operator": "SemiJoin",
      "properties": {
        "viewName": "semiUp59471010586274569",
        "columns": [
          "",
          "",
          ""
        ],
        "columnAliases": [
          "v31",
          "v1",
          "v29"
        ],
        "probeTable": "semiUp2367610003592225848",
        "buildTable": "role_type AS rt",
        "probeKeys": [
          "v29"
        ],
        "buildKeys": [
          "id"
        ],
        "innerConditions": [
          "(role = 'actor')"
        ],
        "outerConditions": [],
        "terminationPolicy": "ADAPTIVE"
      }
    },
    {
      "operator": "SemiJoin",
      "properties": {
        "viewName": "semiUp4403365035441513549",
        "columns": [
          "",
          "",
          ""
        ],
        "columnAliases": [
          "v31",
          "v15",
          "v22"
        ],
        "probeTable": "semiUp443217924677451287",
        "buildTable": "semiUp59471010586274569",
        "probeKeys": [
          "v31"
        ],
        "buildKeys": [
          "v31"
        ],
        "innerConditions": [],
        "outerConditions": [],
        "terminationPolicy": "ADAPTIVE"
      }
    },
    {
      "operator": "SemiJoin",
      "properties": {
        "viewName": "semiUp8525875765690839738",
        "columns": [
          "id"
        ],
        "columnAliases": [
          "v15"
        ],
        "probeTable": "company_name AS cn",
        "buildTable": "semiUp4403365035441513549",
        "probeKeys": [
          "id"
        ],
        "buildKeys": [
          "v15"
        ],
        "innerConditions": [],
        "outerConditions": [
          "(country_code = '[ru]')"
        ],
        "terminationPolicy": "ADAPTIVE"
      }
    },
    {
      "operator": "SemiJoin",
      "properties": {
        "viewName": "semiDown814531401278717393",
        "columns": [
          "",
          "",
          ""
        ],
        "columnAliases": [
          "v31",
          "v15",
          "v22"
        ],
        "probeTable": "semiUp4403365035441513549",
        "buildTable": "semiUp8525875765690839738",
        "probeKeys": [
          "v15"
        ],
        "buildKeys": [
          "v15"
        ],
        "innerConditions": [],
        "outerConditions": [],
        "terminationPolicy": "ADAPTIVE"
      }
    },
    {
      "operator": "SemiJoin",
      "properties": {
        "viewName": "semiDown7400185418246247539",
        "columns": [
          "id"
        ],
        "columnAliases": [
          "v22"
        ],
        "probeTable": "company_type AS ct",
        "buildTable": "semiDown814531401278717393",
        "probeKeys": [
          "id"
        ],
        "buildKeys": [
          "v22"
        ],
        "innerConditions": [],
        "outerConditions": [],
        "terminationPolicy": "ADAPTIVE"
      }
    },
    {
      "operator": "SemiJoin",
      "properties": {
        "viewName": "semiDown2588855390667269516",
        "columns": [
          "id",
          "title"
        ],
        "columnAliases": [
          "v31",
          "v32"
        ],
        "probeTable": "title AS t",
        "buildTable": "semiDown814531401278717393",
        "probeKeys": [
          "id"
        ],
        "buildKeys": [
          "v31"
        ],
        "innerConditions": [],
        "outerConditions": [
          "(production_year > 2010)"
        ],
        "terminationPolicy": "ADAPTIVE"
      }
    },
    {
      "operator": "SemiJoin",
      "properties": {
        "viewName": "semiDown7386333043065741766",
        "columns": [
          "",
          "",
          ""
        ],
        "columnAliases": [
          "v31",
          "v1",
          "v29"
        ],
        "probeTable": "semiUp59471010586274569",
        "buildTable": "semiDown814531401278717393",
        "probeKeys": [
          "v31"
        ],
        "buildKeys": [
          "v31"
        ],
        "innerConditions": [],
        "outerConditions": [],
        "terminationPolicy": "ADAPTIVE"
      }
    },
    {
      "operator": "SemiJoin",
      "properties": {
        "viewName": "semiDown468745051267498860",
        "columns": [
          "id"
        ],
        "columnAliases": [
          "v29"
        ],
        "probeTable": "role_type AS rt",
        "buildTable": "semiDown7386333043065741766",
        "probeKeys": [
          "id"
        ],
        "buildKeys": [
          "v29"
        ],
        "innerConditions": [],
        "outerConditions": [
          "(role = 'actor')"
        ],
        "terminationPolicy": "ADAPTIVE"
      }
    },
    {
      "operator": "SemiJoin",
      "properties": {
        "viewName": "semiDown9208948583067247042",
        "columns": [
          "id",
          "name"
        ],
        "columnAliases": [
          "v1",
          "v2"
        ],
        "probeTable": "char_name AS chn",
        "buildTable": "semiDown7386333043065741766",
        "probeKeys": [
          "id"
        ],
        "buildKeys": [
          "v1"
        ],
        "innerConditions": [],
        "outerConditions": [],
        "terminationPolicy": "ADAPTIVE"
      }
    },
    {
      "operator": "Select",
      "properties": {
        "viewName": "aggView764197541071045443",
        "columns": [
          ""
        ],
        "columnAliases": [
          "v29"
        ],
        "inputView": "semiDown468745051267498860",
        "conditions": [],
        "groupBy": []
      }
    },
    {
      "operator": "Join",
      "properties": {
        "viewName": "aggJoin5998824771054267538",
        "columns": [
          "",
          ""
        ],
        "columnAliases": [
          "v31",
          "v1"
        ],
        "probeTable": "semiDown7386333043065741766",
        "buildTable": "aggView764197541071045443",
        "joinKeys": [
          "v29"
        ],
        "conditions": []
      }
    },
    {
      "operator": "Select",
      "properties": {
        "viewName": "aggView6646160625512734913",
        "columns": [
          "",
          "v32"
        ],
        "columnAliases": [
          "v31",
          "v44"
        ],
        "inputView": "semiDown2588855390667269516",
        "conditions": [],
        "groupBy": []
      }
    },
    {
      "operator": "Join",
      "properties": {
        "viewName": "aggJoin6142552546527301193",
        "columns": [
          "",
          "",
          "",
          ""
        ],
        "columnAliases": [
          "v31",
          "v15",
          "v22",
          "v44"
        ],
        "probeTable": "semiDown814531401278717393",
        "buildTable": "aggView6646160625512734913",
        "joinKeys": [
          "v31"
        ],
        "conditions": []
      }
    },
    {
      "operator": "Select",
      "properties": {
        "viewName": "aggView1872660562829076552",
        "columns": [
          "",
          "v2"
        ],
        "columnAliases": [
          "v1",
          "v43"
        ],
        "inputView": "semiDown9208948583067247042",
        "conditions": [],
        "groupBy": []
      }
    },
    {
      "operator": "Join",
      "properties": {
        "viewName": "aggJoin6439808983944348849",
        "columns": [
          "",
          ""
        ],
        "columnAliases": [
          "v31",
          "v43"
        ],
        "probeTable": "aggJoin5998824771054267538",
        "buildTable": "aggView1872660562829076552",
        "joinKeys": [
          "v1"
        ],
        "conditions": []
      }
    },
    {
      "operator": "Select",
      "properties": {
        "viewName": "aggView8255487806198462729",
        "columns": [
          ""
        ],
        "columnAliases": [
          "v22"
        ],
        "inputView": "semiDown7400185418246247539",
        "conditions": [],
        "groupBy": []
      }
    },
    {
      "operator": "Join",
      "properties": {
        "viewName": "aggJoin1840096498860502358",
        "columns": [
          "",
          "",
          ""
        ],
        "columnAliases": [
          "v31",
          "v15",
          "v44"
        ],
        "probeTable": "aggJoin6142552546527301193",
        "buildTable": "aggView8255487806198462729",
        "joinKeys": [
          "v22"
        ],
        "conditions": []
      }
    },
    {
      "operator": "GroupBy",
      "properties": {
        "viewName": "aggView2429241620730436849",
        "columns": [
          "",
          "MIN(v43)"
        ],
        "columnAliases": [
          "v31",
          "v43"
        ],
        "inputView": "aggJoin6439808983944348849",
        "conditions": [],
        "groupBy": [
          "v31",
          "v43"
        ],
        "terminationPolicy": "ADAPTIVE"
      }
    },
    {
      "operator": "Join",
      "properties": {
        "viewName": "aggJoin6043250212083338434",
        "columns": [
          "",
          "v44",
          ""
        ],
        "columnAliases": [
          "v15",
          "v44",
          "v43"
        ],
        "probeTable": "aggJoin1840096498860502358",
        "buildTable": "aggView2429241620730436849",
        "joinKeys": [
          "v31"
        ],
        "conditions": []
      }
    },
    {
      "operator": "GroupBy",
      "properties": {
        "viewName": "aggView6723037927410477405",
        "columns": [
          "",
          "MIN(v44)",
          "MIN(v43)"
        ],
        "columnAliases": [
          "v15",
          "v44",
          "v43"
        ],
        "inputView": "aggJoin6043250212083338434",
        "conditions": [],
        "groupBy": [
          "v15",
          "v43",
          "v44"
        ],
        "terminationPolicy": "NONE"
      }
    },
    {
      "operator": "Join",
      "properties": {
        "viewName": "aggJoin3496838090076012500",
        "columns": [
          "",
          ""
        ],
        "columnAliases": [
          "v44",
          "v43"
        ],
        "probeTable": "semiUp8525875765690839738",
        "buildTable": "aggView6723037927410477405",
        "joinKeys": [
          "v15"
        ],
        "conditions": []
      }
    },
    {
      "operator": "Select",
      "properties": {
        "viewName": "finalResult",
        "columns": [
          "MIN(v43)",
          "MIN(v44)"
        ],
        "columnAliases": [
          "v43",
          "v44"
        ],
        "inputView": "aggJoin3496838090076012500",
        "conditions": []
      }
    }
  ]
}